pc_monitor_server/__init__.py
pc_monitor_server/__main__.py
pc_monitor_server/main.py
pc_monitor_server/util.py
pc_monitor_server/version.py
pc_monitor_server-1.2.2.dist-info/METADATA
pc_monitor_server-1.2.2.dist-info/WHEEL
pc_monitor_server-1.2.2.dist-info/entry_points.txt
pc_monitor_server-1.2.2.dist-info/top_level.txt
pc_monitor_server-1.2.2.dist-info/RECORD
